pyro/__init__.py
pyro/analysis/__init__.py
pyro/analysis/costfunction.py
pyro/analysis/graphical.py
pyro/analysis/phaseanalysis.py
pyro/analysis/simulation.py
pyro/control/__init__.py
pyro/control/controller.py
pyro/control/linear.py
pyro/control/lqr.py
pyro/control/nonlinear.py
pyro/control/reinforcementlearning.py
pyro/control/robotcontrollers.py
pyro/dynamic/__init__.py
pyro/dynamic/boat.py
pyro/dynamic/cartpole.py
pyro/dynamic/drone.py
pyro/dynamic/equation.py
pyro/dynamic/integrator.py
pyro/dynamic/manipulator.py
pyro/dynamic/massspringdamper.py
pyro/dynamic/mechanical.py
pyro/dynamic/mountaincar.py
pyro/dynamic/pendulum.py
pyro/dynamic/plane.py
pyro/dynamic/rigidbody.py
pyro/dynamic/rocket.py
pyro/dynamic/statespace.py
pyro/dynamic/suspension.py
pyro/dynamic/system.py
pyro/dynamic/tranferfunction.py
pyro/dynamic/vehicle_propulsion.py
pyro/dynamic/vehicle_steering.py
pyro/kinematic/__init__.py
pyro/kinematic/drawing.py
pyro/kinematic/geometry.py
pyro/planning/__init__.py
pyro/planning/discretizer.py
pyro/planning/dynamicprogramming.py
pyro/planning/filters.py
pyro/planning/plan.py
pyro/planning/randomtree.py
pyro/planning/trajectorygeneration.py
pyro/planning/trajectoryoptimisation.py
pyro/tools/__init__.py
pyro/tools/sys2gym.py
pyro_udes-3.0.dist-info/METADATA
pyro_udes-3.0.dist-info/WHEEL
pyro_udes-3.0.dist-info/licenses/LICENSE
pyro_udes-3.0.dist-info/RECORD
