Metadata-Version: 2.3
Name: pyro_udes
Version: 3.0
Summary: object-based toolbox for robot dynamic simulation, analysis, control and planning
Project-URL: Homepage, https://github.com/SherbyRobotics/pyro/tree/master
Author-email: Alexandre Girard <alx87grd@gmail.com>, Ian Lalonde <lali3401@usherbrooke.ca>
Classifier: Intended Audience :: Science/Research
Classifier: License :: OSI Approved :: MIT License
Classifier: Operating System :: OS Independent
Classifier: Programming Language :: Python :: 3
Classifier: Topic :: Scientific/Engineering
Requires-Python: >=3.5
Requires-Dist: matplotlib>=3.0
Requires-Dist: numpy>=1.10
Requires-Dist: scipy>=1.5.2
